{"id":"181986","urlID":"3c6r6","name":"match2","description":"","content":"Session Information\n\nSpecification: msl2_1_rx2_file\nSession ID: 2015\/11\/13-19\nType: Backup\nSession Owner: mycompany.com\nStatus: Completed\nMode: incr\nStart Time: 11\/13\/2015 12:07:33 PM\nQueuing: 0:00\nDuration: 2:24\nGB Written: 596.05\n# Media: 2\n# Errors: 1\n# Warnings: 0","weightedVote":"2.5","numVotes":"0","author":"bigeast","community":"1","dateAdded":"2015-11-13","pattern":"(Specification: (.+))|(# Errors:\\ (.+))","replace":"","state":"{\"substEnabled\":false}"}