{"id":"181668","urlID":"3c5tc","name":"casasalud","description":"sd","content":"CADERA AP\/AXIAL \nR. LUMBAR AP\/L\nNum Informe: CAD:641377 \nLUM: 641376\nEl  estudio  de  la  columna  lumbar  realizado  proyecci\u00f3n  anteroposterior  lateral,   pone   de \nmanifiesto: \nNormal alineaci\u00f3n de los somas vertebrales lumbaressin imagen de listesis. Se aprecian \nleves  rasgos  osteocondr\u00f3ticos  con  algunas  peque\u00f1as  osteofitosis  marginales  en  los \nrebordes de los somas, sobre todo a nivel caudal. \nArticulaciones  interapofisarias  de  morfolog\u00eda  conservada.  Discos  intervertebrales  de \nmorfolog\u00eda  conservada,   salvo  a  nivel  de  L5-S1  donde  se  aprecia  discreto  pinzamiento, \nque puede sugerir cambios degenerativos. \nArticulaciones sacroil\u00edacas normales. \nEl estudio de caderas realizado en proyecci\u00f3n anteroposterior pone manifiesto una normal \nmorfolog\u00eda y densidad del esqueleto visualizado. \nAmbas  caderas  con  interl\u00edneas  articulares  conservadas.  Discreta  hipertrofia  de  los \nrebordes  acetabulares  de  car\u00e1cter  degenerativo.  Morfolog\u00eda  de  las  cabezas  femorales \nconservada. \nNo apreciamos im\u00e1genes de trazos de fracturas o lesiones l\u00edticas o bl\u00e1sticas. \nAtentamente, \nDr. FRANCISCO JAVIER LOPEZ GOMIS \nCol. 464611229 \nEstado del Informe Validado \/ Dr. LOPE","weightedVote":"2.5","numVotes":"0","author":"me","community":"1","dateAdded":"2015-11-10","pattern":"Num Informe: \\s+([0-9]{6})\\b","replace":"","state":"{\"substEnabled\":false}"}