{"id":"163033","urlID":"3afab","name":"lobuljen2","description":"lobuljen1","content":"   30. DISIDENT - ZIVOT JE... (3:43)\n   31. GRUPA BANANA - GRUPA BANANA feat. JIMMY MATESIC-Jablan (3:08)\n   32. JELENA ROZGA - OBOZAVAM (3:56)\n   33. HARI RON\u010cEVI\u0106 - PONOVO ZNAM (5:11)\n   34. TOSE PROESKI - Sve je ovo premalo za kraj (Official Music Video 2013) \n  (3:35)\n   35. Ivana Banfic - Zlatno Pravilo (Official Music Video) (3:27)\n   36. ET - PRI\u0110I BEZ RAZLOGA (official video) --- - --- (4:14)\n   37. Massimo - Suze nam stale na put (4:41)\n   38. GIULIANO - TULUM (3:53)\n   39. Jasmin Stavros- Opala (TV SPOT) (3:20)\n   40. KLAPA VELA LUKA PROIZD - ZEMLJA DIDE MOG (3:58)\n   41. SINOVI RAVNICE & COLONIA - LJUBAVNICI (3:50)\n   42. Globus Band - Kad te poljubim (4:03)\n   43. IVANA MARIC - Tko si mi ti (3:32)\n   44. The Ventures - Mexico (2:52)\n   45. Goran Karan - Jesen stize dunjo moja (3:55)\n   46. Ivan Zak - Sla\u017ei jo\u0161 ve\u010deras (album \"Bolja od najbolje\" 2012) (3:38)\n   47. IVANA KOVAC - NIMA SOLDI, E, PA CA (SPLITSKI FESTIVAL - AUDIO 2013.) \n  (3:04)\n   48. Jasmin Stavros- Ju\u017enije, manje tu\u017enije (OFFICIAL AUDIO) (3:39)\n   49. Kajda - Golubek Moj Beli (3:39)\n   50. Fiskali - Lovec (2:46)\n   51. Brujaci - Valcer (4:29)\n   52. F. Knezevic i TS Berdeband - Moje jedino (4:44)\n   53. Juraj Galina & Petkovecki Tamburasi - Prvi Pogled Ljubavi (3:13)\n   54. Kavaliri - K\u00fcmevo Klijet (3:19)\n   55. Lepi Cajti - Barek i Rozita (3:13)\n   56. Mili & Kajda - Senje (3:12)\n   57. Mirko Svenda Ziga - Srce Medimurko (3:10)\n   58. Mladi Muzikasi - Snjezana (3:59)\n   59. SPORTSKA EMISIJA FINALE (39:4","weightedVote":"2.5","numVotes":"0","author":"lobuljen1","community":"1","dateAdded":"2015-02-20","pattern":"\\s\\s\\(\\d{1,2}:\\d{1,2}\\)","replace":"","state":""}