{"id":"176757","urlID":"3bngv","name":"micke","description":"short url matcher","content":"http:\/\/someuser:password@www.website.com\/path\/to\/file.ext?query=something&parameters=passed#with-anchor\nhttps:\/\/subdomain.mobile.de\nwww.mobile.de\n\ninvalidurl.de\nwww.invalid#bla\nhttp:\/\/invalidurl?parmeter=0","weightedVote":"2.5","numVotes":"0","author":"","community":"1","dateAdded":"2015-09-04","pattern":"(https?:\\\/\\\/(?:www\\.|(?!www))[^\\s\\.]+\\.[^\\s]{2,}|www\\.[^\\s]+\\.[^\\s]{2,})","replace":"Protocol:\\t$2\\nUser:\\t\\t\\t$4\\nPassword:\\t$5\\nDomain:\\t\\t$6\\nRequest:\\t\\t$9\\nQuery:\\t\\t$10\\nAnchor:\\t\\t$11","state":"{\"substEnabled\":true}"}