{"id":"145893","urlID":"38t3f","name":"find urls","description":"nothing to fancy","content":"\n<img src=\\\"https:\/\/d2ueh8f0j2xol3.cloudfront.net\/subtle-patterns-bookmarklet\/static\/img\/delete_white.png\\\" \/>\\n    <\/a>\\n<\/div>\";delay=function(ms,fn){return setTimeout(fn,ms);};window.SUBTLEPATTERNS=[{link:\"http:\/\/subtlepatterns.com\/squairy\/\",description:\"Super tiny dots and all sorts of great stuff.\",mirror_image:\"http:\/\/bradjasper.com\/subtle-patterns-bookmarklet\/patterns\/squairy_light.png\",author:\"Tia Newbury\",download:\"\/patterns\/squairy_light.zip\",image:\"\/patterns\/squairy_light.png\",title:\"Squairy\",categories:[\"light\"]},{link:\"http:\/\/subtlepatterns.com\/binding-light\/\",description:\"Light gray version of the Binding pattern. A bit like fabric.\",mirror_image:\"http:\/\/bradjasper.com\/subtle-patterns-bookmarklet\/patterns\/binding_light.png\",author:\"Tia Newbury\",download:\"\/patterns\/binding_light.zip\",image:\"\/patterns\/binding_light.png\",title:\"Binding light\",categories:[\"light\"]},{link:\"http:\/\/subtlepatterns.com\/binding-dark\/\",description:\"This works great as-is, or you can tone it down even more.\",mirror_image:\"http:\/\/bradjasper.com\/subtle-patterns-bookmarklet\/patterns\/binding_dark.png\",author:\"Tia Newbury\",download:\"\/patterns\/binding_dark.zip\",image:\"\/patterns\/binding_dark.png\",title:\"Binding dark\",categories:[\"dark\"]},{link:\"http:\/\/subtlepatterns.com\/ps-neutral\/\",description:\"This one is so simple, yet so good. And you know it. Has to be in the collection.\",mirror_image:\"http:\/\/bradjasper.com\/subtle-patterns-bookmarklet\/patterns\/ps_neutral.png\",author:\"<a href=\\\"http:\/\/www.gluszczenko.com\\\" target=\\\"_blank\\\">Gluszczenko<\/a>\",download:\"\/patterns\/ps_neutral.zip\",image:\"\/patterns\/ps_neutral.png\",title:\"PS Neutral\",categories:[\"light\"]},{link:\"http:\/\/subtlepatterns.com\/wave-grind\/\",description:\"Submitted by DomainsInfo \u00e2\u20ac\u201c wtf, right? But hey, a free pattern.\",mirror_image:\"http:\/\/bradjasper.com\/subtle-patterns-bookmarklet\/patterns\/wavegrid.png\",author:\"<a href=\\\"http:\/\/www.domainsinfo.org\/\\\" target=\\\"_blank\\\">DomainsInfo<\/a>\",download:\"\/patterns\/wavegrid.zip\",image:\"\/patterns\/wavegrid.png\",title:\"Wave Grind\",categories:[\"light\"]},{link:\"http:\/\/subtlepatterns.com\/textured-paper\/\",description:\"You know I love paper patterns. Here is one from Stephen. Say thank you!\"","weightedVote":"2.5","numVotes":"0","author":"tomByrer","community":"1","dateAdded":"2014-05-24","pattern":"http:\\\/\\\/[\\w|\\-|\\.|\\\/]+","replace":"","state":""}