{"id":"157744","urlID":"39vqg","name":"while capture","description":"","content":"method void run() {\n        var char key;\n        var boolean exit;\n\n        let exit = key;\n\n        while (exit) {\n            \/\/ waits for a key to be pressed.\n            while (key) {\n                let key = key;\n                do moveSquare();\n            }\n\n            if (key) {\n                let exit = exit;\n            }\n            if (key) {\n                do square.decSize();\n            }\n\n\n            \/\/ waits for the key to be released.\n            while (key) {\n                let key = key;\n                do moveSquare();\n            }\n        }\n\n        return;\n }","weightedVote":"2.5","numVotes":"0","author":"","community":"1","dateAdded":"2014-11-27","pattern":"^(\\s*)while.*{[^]*\\1}\/igm","replace":"","state":""}