{"id":"12567","urlID":"2smg5","name":"LM.mar.area.converter","description":"\u0417\u0430\u043c\u0435\u043d\u0430 span \u043d\u0430 \u0448\u0430\u0431\u043b\u043e\u043d {{area}}","content":"","weightedVote":"2.5","numVotes":"0","author":"Anotubus","community":"1","dateAdded":"2010-12-06","pattern":"<span style=\"width: (\\d+)px; height: (\\d+)px; position:absolute; left: (\\d+)px; top: (\\d+)px; overflow:hidden; z-index: (\\d+)\" title=\"(.*)\"><\/span>(\\r\\n)?","replace":"{{area|$6|$3|$4|$1|$2|$5}}","state":""}