{"id":"167843","urlID":"3atd9","name":"North Amer Phone Numbers","description":"pattern for north american phone number validation","content":"p:444-555-1234 \nf:246.555.8888 \nm:1235554567 invalid area code starts with \"1\"\nt:(222) 243-2312 \nX:(205)555-1234\nl: 1(205)555-1212 long distance code","weightedVote":"2.5","numVotes":"0","author":"MJudson","community":"1","dateAdded":"2015-04-28","pattern":"[1]?[(]?[2-9]\\d{2}[-.)]?[ ]?[2-9]\\d{2}[-.]?\\d{4}\\b","replace":"","state":"{\"substEnabled\":false}"}