{"id":"178675","urlID":"3bt4p","name":"Email","description":"","content":"Acceptable\n---------------\ncat-nut@q.com\nbilly@aol.com\nbro.dad@aol-bot.com\nabc1.1@domain.com\nroman@99percentinvisible.org\nakimex0101@cf.em-net.ne\nakimex0101@cf.em-net.ne.jp\nakimex0101@em-net.com\nabc.abc@domain.com\nabc_41.15768@domain.com\n12345@domain.com\n12.12.23@domain.com\nABC.ABC.ABC.ABC0046@domain.com\nabc_123_4595@domain.com\nabc@asdas.co.in\nabc@insta123.com\nabc@inta.co.in\n208travel@medicaid.dhs.state.hi.us\ndental@ccmcorp.net\n\nNon-Acceptable\n---------------\na@b.c\na@.com\nbilly@aol\nexample@domain_domain.com\nabc1.1@-domain.com\nabc@@insta.com.com.com\nabc@insta..com\nabc@insta%.com\nabc@insta\/.com\nabc@insta\\.com\nabc..abc@domain.com \nabc__abc@domain.com\nabc.@insta.com\nabc..de@insta.com\nabc-@insta.com\nabc-def@insta.com\nabc+@insta.com\nabc123..45@insta.com\nabc%@insta.com\nabc\\@insta.com\nabc\/@insta.com\nabc@insta-.com\nABC.ABC.ABC.ABC0046@domain.com.com.com","weightedVote":"2.5","numVotes":"0","author":"Jamie Perkins","community":"1","dateAdded":"2015-09-30","pattern":"^[\\w\\d\\+\\.\\-]+@[a-zA-Z\\d\\.\\-]+\\.[a-zA-Z]{2,15}$\/igm","replace":"","state":"{\"substEnabled\":false}"}