{"id":"13883","urlID":"2sqbh","name":"Date MMddyy v1.1 (leap year still excluded)","description":"This is more like a Brute force method. Since I didn't find a good one for myself, thought I'll create one.\r\rIMP NOTE: Doesn't check for leap years. All months in feb have 28days !!\r\rPS: I'm new to RegEx\r\rFixes:\rv1.1: Feb dates like 021909 were not matching earlier","content":"","weightedVote":"3.26389","numVotes":"1","author":"Aviral Sharma","community":"1","dateAdded":"2010-12-29","pattern":"\/([0][13578]|[1][02])([0][1-9]|[1-2][0-9]|[3][0-1])([0-9][0-9])|([0][469]|[1][1])([0][1-9]|[1-2][0-9]|[3][0])([0-9][0-9])|([0][2])([0][1-9]|[1][0-9]|[2][0-8])([0-9][0-9])\/gixsm","replace":"","state":""}