{"id":"150053","urlID":"3999f","name":"Row Name Selection New","description":"Selects a Row with the name \"Chima\"","content":"USER       PID %CPU %MEM    VSZ   RSS TTY      STAT START   TIME COMMAND\nroot      1260  0.0  0.0  17036   756 tty4     Ss+  Jul10   0:00 \/sbin\/getty -8 38400 tty4\nroot      1266  0.0  0.0  17036   756 tty5     Ss+  Jul10   0:00 \/sbin\/getty -8 38400 tty5\nroot      1281  0.0  0.0  17036   756 tty2     Ss+  Jul10   0:00 \/sbin\/getty -8 38400 tty2\nroot      1283  0.0  0.0  17036   756 tty3     Ss+  Jul10   0:00 \/sbin\/getty -8 38400 tty3\nroot      1285  0.0  0.0  17036   756 tty6     Ss+  Jul10   0:00 \/sbin\/getty -8 38400 tty6\nroot      1817  0.0  0.0  17036   756 tty1     Ss+  Jul10   0:00 \/sbin\/getty -8 38400 tty1\npozar    17382  0.0  0.0  25788  5656 pts\/7    Ss+  Aug04   0:00 \/bin\/bash\nmarek    22598  0.0  0.0  25568  5492 pts\/10   Ss   Aug01   0:00 \/bin\/bash\nghik     25194  0.0  0.0  29760  9644 pts\/1    Ss   08:46   0:00 -bash\nghik     25320  0.0  0.0  26216  1716 pts\/1    S+   08:46   0:00 socat -v tcp-listen:20372,fork tcp:10.10.255.242:10301\nchima    25543  0.0  0.0  29700  9672 pts\/2    Ss   09:22   0:00 -bash\nchima    25666  0.0  0.1  50124 11856 pts\/2    T    09:22   0:02 \/usr\/bin\/python .\/logtail.py C83A35-c83a3506b480\nchima    25667  0.2  4.1 3739584 429956 pts\/2  Tl   09:22   0:27 java -cp config:lib\/*:extlib\/* com.avsystem.ump.launcher.logtail.Logtail C83A35-c83a3506b480\nmarek    26227  0.0  0.0  29764  9688 pts\/3    Ss   10:26   0:00 -bash\nmarek    26729  0.0  0.0  28120  1160 pts\/3    S+   11:34   0:00 screen -r mobinnet_socat\nroot     26736  0.0  0.0  57420  2100 pts\/10   S+   11:35   0:00 sudo socat -v TCP-LISTEN:20322,fork TCP:10.10.255.248:10301\nroot     26737  0.0  0.0  26216  1716 pts\/10   S+   11:35   0:00 socat -v TCP-LISTEN:20322,fork TCP:10.10.255.248:10301\nroot     27011  0.0  0.0  57144  1856 pts\/2    T    11:49   0:00 sudo cat\nroot     27013  0.0  0.0   8432   352 pts\/2    T    11:49   0:00 cat\nchima    27246  0.0  0.0  19408  1232 pts\/2    R+   12:03   0:00 ps -au\nchima    27745  0.0  1.0  25346  3634 pts\/2    Ss   11:45   0.00 \/bash\/dummy\/bully\n","weightedVote":"2.5","numVotes":"0","author":"Okehie Chima","community":"1","dateAdded":"2014-08-06","pattern":"\/c\\D\\w+a\\s{4}2\\d{4}(\\s{2}\\d\\.\\d){2}(\\s+\\d{4,7}){2}\\spts\\\/2\\s+\\w+(\\+\\s+\\d{2}:\\d{2}\\s{3}\\d:\\d{2}\\s\\w+\\s-\\w+|\\s{2,}(\\d{2}:\\d{2})\\s{3}\\d:\\d{2}\\s(\\w+\\s-\\w+\\s\\w+:\\w+\\\/\\*:\\w+\\\/\\*|\\-\\w+|(\\\/\\w+)+\\s.\\\/\\w+.\\w+\\s\\w+-\\w+))\/g","replace":"","state":""}