{"id":"153311","urlID":"39iqt","name":"demo","description":"","content":"http:\/\/techdissected.com\/wp-content\/uploads\/2014\/09\/google-fiber-rabbit-11-110x61.jpg?6da9e4\n\nhttp:\/\/techdissected.com\/wp-content\/uploads\/2014\/09\/Nixeus-Headphones-Featured-Image-110x41.jpg?6da9e4\n\nhttp:\/\/techdissected.com\/wp-content\/uploads\/2014\/03\/Ampedlogo_rac15a_featured-110x94.jpg?6da9e4","weightedVote":"2.5","numVotes":"0","author":"","community":"1","dateAdded":"2014-09-25","pattern":"\/(-[\\d]+)x([\\d]+)\/g","replace":"","state":""}