{"id":"157737","urlID":"39vpr","name":"html tag","description":"","content":"\n\n<!DOCTYPE html>\n<html lang=\"en\">\n<head>\n\t<meta charset=\"utf-8\">\n\t<title>Gymn\u00e1zium a st\u0159edn\u00ed \u0161kola EDUCAnet Praha - EDUCAnet Praha<\/title>\n\t<meta name=\"viewport\" content=\"width=device-width, initial-scale=1.0\"   \/>\n\t<meta name=\"description\" content=\"\">\n\t<meta name=\"author\" content=\"\">\n\t<link href=\"common\/css\/bootstrap.css\" rel=\"stylesheet\">\n\t<link href=\"common\/css\/bootstrap-responsive.css\" rel=\"stylesheet\">\n        <link href=\"http:\/\/zs.educanet.cz\/common\/jqueryui\/jquery-ui.css\" rel=\"stylesheet\">\n\t<script src=\"common\/js\/jquery.min.js\"><\/script>\n\n\n\n\t<!--[if lt IE 9]>\n\t\t<script src=\"http:\/\/html5shim.googlecode.com\/svn\/trunk\/html5.js\"><\/script>\n\t<![endif]-->\n\t<link rel=\"shortcut icon\" href=\"common\/ico\/favicon.ico\">\n\t<link rel=\"apple-touch-icon-precomposed\" sizes=\"144x144\" href=\"common\/ico\/apple-touch-icon-144-precomposed.png\">\n\t<link rel=\"apple-touch-icon-precomposed\" sizes=\"114x114\" href=\"common\/ico\/apple-touch-icon-114-precomposed.png\">\n\t<link rel=\"apple-touch-icon-precomposed\" sizes=\"72x72\" href=\"common\/ico\/apple-touch-icon-72-precomposed.png\">\n\t<link rel=\"apple-touch-icon-precomposed\" href=\"common\/ico\/apple-touch-icon-57-precomposed.png\">\n\t\n<base href=\"http:\/\/praha.educanet.cz\/\" \/>\n<meta name=\"Generator\" content=\"CMS Made Simple - Copyright (C) 2004-11 Ted Kulp. All rights reserved.\" \/>\n\n<script type=\"text\/javascript\">\n\n  var _gaq = _gaq || [];\n  _gaq.push(['_setAccount', 'UA-12887525-3']);\n  _gaq.push(['_trackPageview']);\n\n  (function() {\n    var ga = document.createElement('script'); ga.type = 'text\/javascript'; ga.async = true;\n    ga.src = ('https:' == document.location.protocol ? 'https:\/\/ssl' : 'http:\/\/www') + '.google-analytics.com\/ga.js';\n    var s = document.getElementsByTagName('script')[0]; s.parentNode.insertBefore(ga, s);\n  })();\n\n<\/script>\n\n\n<style>\n\n.ui-front {\n  z-index: 10000 !important;\n}\n\n<\/style>\n\n<!--css for show1-->\n<link rel=\"stylesheet\" type=\"text\/css\" href=\"http:\/\/praha.educanet.cz\/modules\/Showtime\/templates\/css\/Show_1.css\" \/>\n<!--LOAD SHOWTIME nivoslider-->\n<script type=\"text\/javascript\" src=\"http:\/\/praha.educanet.cz\/modules\/Showtime\/templates\/nivoslider\/jquery.nivo.slider.pack.js\"><\/script>\n<!--END SHOWTIME-->\n<\/head><body>\n\n<div id=\"fb-root\"><\/div>\n\n\n<script>(function(d, s, id) {\n  var js, fjs = d.getElementsByTagName(s)[0];\n  if (d.getElementById(id)) return;\n  js = d.createElement(s); js.id = id;\n  js.src = \"\/\/connect.facebook.net\/en_US\/all.js#xfbml=1&appId=179547045436609\";\n  fjs.parentNode.insertBefore(js, fjs);\n}(document, 'script', 'facebook-jssdk'));<\/script>\n\n\n\n<div class=\"navbar navbar-inverse navbar-fixed-top\">\n<div class=\"navbar-inner\">\n<div class=\"container\">\n\n<div class=\"pull-left\"><a href=\"\/\" class=\"logo\"><h2>EDUCAnet Praha<\/h2><\/a><\/div>\n<div class=\"pull-right\"><ul class=\"edlinks\">\n<li><a href=\"http:\/\/eis.desmodus.cz\" target=\"_blank\"><img src=\"\/uploads\/images\/links\/eis.png\" alt=\"EIS\" width=\"96\" height=\"96\" \/><\/a><\/li>\n<li><a title=\"Bakal\u00e1\u0159i\" href=\"http:\/\/77.48.61.186\/\" target=\"_blank\"><img src=\"uploa","weightedVote":"2.5","numVotes":"0","author":"","community":"1","dateAdded":"2014-11-27","pattern":"((<[!]?\\w+(?:\\s+\\w+(?:=\"[^\"]*\")?)*(?:\\s+\\\/)?>)(?:([^<]*)<\\\/\\w+>)?)","replace":"","state":""}