{"id":"158546","urlID":"3a25m","name":"queyr","description":"","content":"SEL EMOPLYE\nSELAMS HOME CARE\nSELCAT\nSELCO MANUFACTURUNG\nSELDERHOSS BROS DRILLING\nSELDIN SECURITY\nSELEC STAFFING\nSELECT\nSELECT A PRODUCT\nSELECT AIRE\nSELECT BUILDING SERVICES\nSELECT COM\nSELECT COM PRODUCT\nSELECT COMFORT\nSELECT DRILLING\nSELECT ENEREGY SERVICES\nSELECT ENERGY\nSELECT ENERGY SERVICES\nSELECT EVALUATION\nSELECT FLEET SERVICES\nSELECT FOOD SERVICES\nSELECT FRAME SHOP\nSELECT GROUP\nSELECT HOME CARE\nSELECT HOSIPATAL\nSELECT HOSPETAL\nSELECT HOSPITAL\nSELECT HOTELS\nSELECT INC\nSELECT MANAGEMENT\nSELECT MECHANICAL\nSELECT MEDICAL\nSELECT MEDICAL CENTER\nSELECT MERCHANT SERVICES\nSELECT OILFIELD\nSELECT OPTICAL\nSELECT PEOPLE INC\nSELECT PLUMBING\nSELECT PORTFOLIO SERV\nSELECT QUOTE\nSELECT QUOTE SR\nSELECT REMEDY\nSELECT REMEDY STAFFING\nSELECT RESOURCE GROUP\nSELECT RIDE\nSELECT SERVICES\nSELECT SOURCE\nSELECT SPEC HOSP\nSELECT SPECIAL\nSELECT SPECIAL HOSP\nSELECT SPECIALTY\nSELECT SPECIALTY HOSPITAL\nSELECT STAFF\nSELECT STAFFING\nSELECT STAFFING TECHNICOLOR\nSELECT STAINLESS\nSELECT TECH\nSELECTCOM\nSELECTED FURNITURE\nSELECTION STUFFING\nSELECTIVE CASE MANAGMENT\nSELECTIVE HEALTHCARE\nSELECTIVE HOMES\nSELECTIVE TRANSPORTATION\nSELECTRIC\nSELENAS DAYCARE\nSELESOURCE\nSELEX LLC\nSELF\nSELF  EMPLOYED\nSELF BRIDS\nSELF CLEANING SERVICE\nSELF CONTRACTOR\nSELF DEEP SOUTH BUILDER\nSELF DETERMINATION PROGAM\nSELF EMP. RES SERV PROVIDER\nSELF EMPL\nSELF EMPL;OYED\nSELF EMPLOY\nSELF EMPLOYE\nSELF EMPLOYED\nSELF EMPLOYED \/\nSELF EMPLOYED CAREGIVER\nSELF EMPLOYED CONTRACTOR\nSELF EMPLOYED INTEGRITY\nSELF EMPLOYED LAWN SERVICE\nSELF EMPLOYED SALON WEST\nSELF EMPLOYED-GRADUATE ST\nSELF EMPLOYEE\nSELF EMPLOYEED\nSELF EMPLOYMENT\nSELF ENTERPRISES\nSELF GRAPHIC DESIGNER\nSELF HOME DAYCARE\nSELF INC\nSELF INDUSTRIES\nSELF NURSING HOME\nSELF OWNER OPERATOR\nSELF REGIONAL\nSELF REGIONAL HOSPITAL\nSELF SSI\nSELF STORAGE\nSELF-EMPLOYED\nSELF-EMPLOYED TRUCK\nSELFEMPLOYED\nSELINK\nSELL CONSTRUCTION CORP\nSELL-THRU SERVICES\nSELLARS\nSELLS BUILDING SUPPLY\nSELMA CITY PUBLIC WORKS\nSELMA POLICE DEPT\nSELMA SCHOOL SYSTEM\nSELMAN CHEVROLET\nSELMET INC","weightedVote":"2.5","numVotes":"0","author":"","community":"1","dateAdded":"2014-12-10","pattern":"\/(sel).(em).\/ig","replace":"","state":""}