{"id":"167984","urlID":"3atqg","name":"Currency Regex","description":"A simple straightforward currency expression.","content":"Welcome to RegExr v2.0 by gskinner.com!\n\nEdit the Expression & Text to see matches. Roll over matches or the expression for details. Undo mistakes with ctrl-z. Save & Share expressions with friends or the Community. A full Reference & Help is available in the Library, or watch the video Tutorial.\n\nSample text for testing:\nabcdefghijklmnopqrstuvwxyz ABCDEFGHIJKLMNOPQRSTUVWXYZ\n0123456789 +-.,!@#$%^&*();\\\/|<>\"'\n12345 -98.7 3.141 .6180 9,000 +42\n555.123.4567\t+1-(800)-555-2468\nfoo@demo.net\tbar.ba@test.co.uk\nwww.demo.com\thttp:\/\/foo.co.uk\/\nhttp:\/\/regexr.com\/foo.html?q=bar\n\n\u20ac1.54\n$23.50\n\u00a3140\n\u20ac140000000.00\n\u20ac12434566.00\n\u20ac123,000,000,000\ngg\u20ac\n1\n0\nIS123","weightedVote":"2.5","numVotes":"0","author":"Declan Murphy","community":"1","dateAdded":"2015-04-30","pattern":"\/(\\\u20ac|\\$|\\\u00a3|\\\u00a5|\\\u20a9|\\\u20aa|\\\u20b9|(ISK)|(SEK)|(\u0e3f)){1}([1-9]{1}[0-9]{0,2}\\,?[0-9]{0,3}\\,?[0-9]{0,3}\\,?[0-9]{0,3})(\\.\\d\\d)?\/g","replace":"","state":"{\"substEnabled\":false}"}