{"id":"169631","urlID":"3b2kt","name":"clauses properties methods","description":"finds clauses, properties, methods used in AppleScript strings ","content":"-- '!' \u2022 __Choose Folders For Empty Ones (102 lijnen) \u2022 [contrived, scripted, modified by Marcus Bogaert \u00a92015, twistitideas] (15-05-20 om 23:56 uur) pad: \"McMain:Users:marcusbogaert:Dropbox:__Choose Folders For Empty Ones.scptd\"\n\\b(on |end )(?!\\t)(?!(tell|error|if|run|try|script|repeat|timeout|of ))([a-zA-Z0-9]+|[\\)\\:\\(]+).*|(property [\\w]+.*)|(use [\\w]+.*)\n\nuse AppleScript\nuse scripting additions\nuse application \"ASObjC Runner\"\nuse script \"Inserter Utilities\"\nuse ImagesHV : script \"ImagesHV\"\nuse CopyRTF : script \"ASOCFileCopyRTF\"\nuse PathConverter : script \"PathConverter\"\n\nproperty findNameStub : \"([a-z,A-Z,0-9\\\\-\\\\_]+)[\\\\\/]?(?=\\\\\/?$)\"\nproperty findBareName : \"([^\\\\:|\\\\\/]+)[\\\\w+]+(?=\\\\_\\\\d{6}\\\\\/$)\"\nproperty btns : {\"Sluit\", \"Selecteer map...\"} --{\"Nee\", \"Ja\"}\nproperty todayDWNFolder : \"POSIX path of (((path to downloads folder) as text) & do shell script \\\"date \\\\\\\"+%F:\\\\\\\"\\\") as text\"\nproperty dateDWNMain : \"date +%F\"\nproperty dateDWNPrefix : \"do shell script \\\"date +%y%m%d\\\"\"\nproperty bareNames : missing value\nproperty foldersRecord : missing value\nproperty dirList : missing value\nproperty safFrontTabs : \"tell application \\\"Safari\\\" to tell (windows whose name is in name of documents) to tell tabs to {index,name=\\\"Naamloos\\\", do JavaScript \\\"document.title\\\", (\\\"\\\"  & do JavaScript \\\"document.location.href\\\"), do JavaScript \\\"document.location.pathname\\\", its source}\"\nproperty argNM : \"Links containing \"\nproperty recLabels : {\"WindowCount\", \"WindowTabsCount\", \"TabIndexes\", \"TabTexts\", \"TabNames\", \"TabPosix\", \"TabPathItems\", \"TabTexts\"}\nproperty lookForStuff : \"(http[s]?|\\\\?[s]?[=]?|www|com|php|\\\\?|\\\\=|\\\\#|[0-9]|(PinkFineArt)|( from )|(galleries)|(MacScripter)|(\\\\()|(\\\\))|(\\\\&)|(@)|(-)|(:)|(\\\\|)|(\\\\.)|(\\\\_)|(\u00ab)|(\u00bb)|(>)|(<)|(-)|(,)|(\/)|(\u2022)|( com )|( net )|( org )|(porn )|( url )|(imagefap)|( by )|( with )|(PRIVI[.]?NET)|\\\\+)\"\nproperty folInfos : {\"\u00abpnam\u00bb\", \"\u00abptsz\u00bb\", \"\u00abposx\u00bb\"} --{\"\u00abkind\u00bb\", \"\u00abc\u00c2p7\u00bb\", \"\u00abpkgf\u00bb\", \"\u00absgrp\u00bb\", \"\u00abcdis\u00bb\", \"\u00abasda\u00bb\", \"\u00abaslk\u00bb\", \"\u00abc\u00c2pe\u00bb\", \"\u00abc\u00c2p3\u00bb\", \"\u00abphys\u00bb\", \"\u00absown\u00bb\", \"\u00abc\u00c2pc\u00bb\", \"\u00abposx\u00bb\", \"\u00abdnam\u00bb\", \"\u00abc\u00c2p8\u00bb\", \"\u00abpnam\u00bb\", \"\u00abc\u00c2pa\u00bb\", \"\u00abc\u00c2p6\u00bb\", \"\u00abutid\u00bb\", \"\u00abpspd\u00bb\", \"\u00ablabi\u00bb\", \"\u00abascd\u00bb\", \"\u00abpvis\u00bb\", \"\u00abctnr\u00bb\", \"\u00abc\u00c2pd\u00bb\", \"\u00abasmo\u00bb\",, \"\u00abptsz\u00bb\", \"\u00abc\u00c2pb\u00bb\", \"\u00abc\u00c2p9\u00bb\"}\nproperty parsedLabels : {\"\u00abc\u00c2pc\u00bb\", \"\u00abe\u00c2p2\u00bb\", \"\u00abe\u00c2p1\u00bb\", \"\u00abc\u00c2p1\u00bb\", \"\u00abnmxt\u00bb\"} --{nameStub, pathComponents, nameStubPath, containingItem,nameExt}\n\nglobal listOfDirs, todayFolder, datePrefix, mainDate, listsOfNames, stateDir, emptyDirs\n\nset emptyDirs to {}\nset h to {}\nset flds to ((choose folder multiple selections allowed 1) as list)\n\non parsePath:thisPath grabbingItems:theLabels\n\ttell (parsed path of (thisPath as text)) to copy it to parsedRec\n\tset nameStub to (value for label \"\u00abc\u00c2pc\u00bb\" in records pars","weightedVote":"3.26736","numVotes":"7","author":"twistitideas","community":"1","dateAdded":"2015-05-24","pattern":"\/\\b(on |end )(?!\\t)(?!(tell|error|if|run|try|script|repeat|timeout|of ))([a-zA-Z0-9]+|[\\)\\:\\(]+).*|(property [\\w]+.*)|(use [\\w]+.*)\/g","replace":"","state":"{\"substEnabled\":false}"}