{"id":"176058","urlID":"3blfe","name":"bookmark","description":"","content":"Mi Telcel http:\/\/mitelcel.telcel.com iTelcel http:\/\/m.itelcel.com Clarom\u00fasica http:\/\/www.claromusica.com Clarodeportes http:\/\/deportes.telcel.com Plugger http:\/\/mx.plugger.com","weightedVote":"2.5","numVotes":"0","author":"","community":"1","dateAdded":"2015-08-25","pattern":"\/^(Mi Telcel (https?\\:\/\/[a-zA-Z0-9\\-\\.]+\\.[a-zA-Z]{2,3}(\/\\S*)?) iTelcel (https?\\:\/\/[a-zA-Z0-9\\-\\.]+\\.[a-zA-Z]{2,3}(\/\\S*)?) Clarom\u00fasica (https?\\:\/\/[a-zA-Z0-9\\-\\.]+\\.[a-zA-Z]{2,3}(\/\\S*)?) Clarodeportes (https?\\:\/\/[a-zA-Z0-9\\-\\.]+\\.[a-zA-Z]{2,3}(\/\\S*)?) Plugger (https?\\:\/\/[a-zA-Z0-9\\-\\.]+\\.[a-zA-Z]{2,3}(\/\\S*)?))$\/g","replace":"","state":"{\"substEnabled\":false}"}