{"id":"177144","urlID":"3bol8","name":"NMEA0183 sentences parser","description":"Parse NMEA0183 sentence(s)\nGrp1 - Talker ID|Propriate specifier\nGrp2 - sentence ID|Proprietary manufacturer ID\nGrp3 - optional proprietary manufacturer data header\nGrp4 - optional sentence data fields\nGrp5 - optional checksum","content":"95305.571,,,,,0,0,,,M,,M,,*41\n$GNGLL,,,,,095305.571,V,N*6D\n$GNGSA,A,1,,,,,,,,,,,,,,,*00\n$GNGSA,A,1,,,,,,,,,,,,,,,*00\n$GNRMC,095305.571,V,,,,,8.43,355.98,100915,,,N*5B\n$GPVTG,355.98,T,,M,8.43,N,15.62,K,N*0F\n$GPZDA,095305.571,10,09,2015,,*51\n$GPGGA,095305.672,,,,,0,0,,,M,,M,,*41\n$GNGLL,,,,,095305.672,V,N*6D\n$GNGSA,A,1,,,,,,,,,,,,,,,*00\n$GNGSA,A,1,,,,,,,,,,,,,,,*00$PMTK300,1000,0,0,0,0$GNRMC,095305.672,V,,,,,9.42,2.26,100915,,,N*5F\n$GPVTG,2.26,T,,M,9.42,N,17.46,K,N*0F\n$GPZDA,095305.672,10,09,2015,,*51\n$GPGGA,095305.773,,,,,0,0,,,M,,M,,*41$CCGPQ,GGA<CR><LF>\n$GNGLL,,,,,095305.773,V,N*6D\n$GNGSA,A,1,,,,,,,,,,,,,,,*00\n$GNGSA,A,1,,,,,,,,,,,,,,,*00\n$GNRMC,095305.773,V,,,,,9.19,2.51,100915,,,N*51\n$GPVTG,2.51,T,,M,9.19,N,17.02,K,N*0","weightedVote":"2.5","numVotes":"0","author":"Vsevolod V Gromov","community":"1","dateAdded":"2015-09-10","pattern":"\/\\$(?:(?:([A-Z]{2})([A-Z]{2})Q)|(?:([A-Z]{2})([A-Z]{3}))|(?:P([A-Z]{3})([^\\*,\\r\\n]+)?)),?([^\\*\\r\\n\\$]+)?(?:\\*([0-9A-F]{2}))?\\r?\\n?\/g","replace":"","state":"{\"substEnabled\":false}"}