{"id":"178833","urlID":"3btjj","name":"Ghost Spam URLs","description":"List of known Ghost Spam Hostname sources","content":"success-seo.com\nvideo--production.com\njustprofit.xyz\n\n\nWelcome to RegExr v2.0 by gskinner.com!\n\nEdit the Expression & Text to see matches. Roll over matches or the expression for details. Undo mistakes with cmd-z. Save & Share expressions with friends or the Community. A full Reference & Help is available in the Library, or watch the video Tutorial.\n\nSample text for testing:\nabcdefghijklmnopqrstuvwxyz ABCDEFGHIJKLMNOPQRSTUVWXYZ\n0123456789 +-.,!@#$%^&*();\\\/|<>\"'\n12345 -98.7 3.141 .6180 9,000 +42\n555.123.4567\t+1-(800)-555-2468\nfoo@demo.net\tbar.ba@test.co.uk\nwww.demo.com\thttp:\/\/foo.co.uk\/\nhttp:\/\/regexr.com\/foo.html?q=bar\n\nsuccess-seo.com\t\n4(40.00%)\n100.00%\n4(40.00%)\n100.00%\n1.00\n00:00:00\n0.00%\n0(0.00%)\n$0.00(0.00%)\n\t2.\tvideo--production.com\t\n4(40.00%)\n100.00%\n4(40.00%)\n100.00%\n1.00\n00:00:00\n0.00%\n0(0.00%)\n$0.00(0.00%)\n\t3.\tandy-carter.com\t\n1(10.00%)\n100.00%\n1(10.00%)\n100.00%\n1.00\n00:00:00\n0.00%\n0(0.00%)\n$0.00(0.00%)\n\t4.\tjustprofit.xyz","weightedVote":"2.5","numVotes":"0","author":"Fernando Seminario","community":"1","dateAdded":"2015-10-02","pattern":"\/(best|100dollars|success)\\-seo|(videos|buttons)\\-for|anticrawler|musica\\-gratis|semalt|forum69|7makemoney|sharebutton|ranksonic|sitevaluation|dailyrank|video--production\\.com|justprofit\\.xyz\/g","replace":"","state":"{\"substEnabled\":false}"}