{"id":"37012","urlID":"2uu3s","name":"Right side of expression","description":"This will get the right side of an expression after the operator. This assumes that the value (right side) contains numbers, digits, or single quotes. This is useful for parsing SQL field='value' strings, or key\/value expressions.\r\rFor example, this will return 43 from the following strings:\rfield = 43, field <= 43, field > 43, etc..","content":"","weightedVote":"3.52041","numVotes":"2","author":"Carol Skelly","community":"1","dateAdded":"2011-10-13","pattern":"[\\\\d\\\\w']+\\\\z","replace":"","state":""}