{"id":"150412","urlID":"39ab4","name":"khccmatching","description":"","content":"{ \"job_id\":\"1\", \"user_name\":\"Doug Read\", \"user_email\":\"jread@fedex.com\", \"alt_user_name\":\"\", \"alt_user_email\":\"cchiavario@fedex.com\", \"job_owner_account_number\":\"270451608\", \"job_owner_company_name\":\"UNILEVER HPC\", \"job_owner_address\":\"5620 INNER PARK DR\", \"job_owner_city\":\"PONTOON BEACH\", \"job_owner_state_province\":\"IL\", \"job_owner_postal_code\":\"62040\", \"job_owner_country\":\"US\", \"job_owner_contact_name\":\" DOUG MAGERS\", \"job_owner_contact_phone\":\"573-395-3197\", \"job_owner_contact_email\":\"dougread1959@gmail.com\", \"bls_production_code\":\"1\", \"return_type_code\":\"0\", \"outbound_special_options\":\"\", \"pickup_country\":\"US\", \"pickup_company_name\":\"UNILEVER HPC\", \"pickup_contact_name\":\" DOUG MAGERS\", \"pickup_address1\":\"5620 INNER PARK DR\"\", \"pickup_address2\":\"\", \"pickup_city\":\"PONTOON BEACH\", \"pickup_state_province\":\"IL\", \"pickup_postal\":\"62040\", \"pickup_phone\":\"573-395-31\", \"pickup_email\":\"dougread1959@gmail.com\", \"sender_country\":\"US\", \"sender_company\":\"UNILEVER HPC\", \"sender_contact\":\" DOUG MAGERS\", \"sender_addr1\":\"5620 INNER PARK DR\"\", \"sender_addr2\":\"\", \"sender_city\":\"PONTOON BEACH\", \"sender_state_province\":\"IL\", \"sender_postal\":\"62040\", \"sender_phone\":\"573-395-3197\", \"outbound_billing_account_number\":\"260913565\", \"outbound_billing_company_name\":\"UNILEVER HPC\/CCD COMM DEPT\", \"outbound_billing_code\":\"2\", \"returns_special_options\":\"\", \"receiver_country\":\"\", \"receiver_company\":\"\", \"receiver_contact\":\"\", \"receiver_address1\":\"\", \"receiver_address2\":\"\", \"receiver_city\":\"\", \"receiver_state_province\":\"\", \"receiver_postal\":\"\", \"receiver_phone\":\"\", \"shipper_country\":\"\", \"shipper_company\":\"\", \"shipper_contact\":\"\", \"shipper_address1\":\"\", \"shipper_address2\":\"\", \"shipper_city\":\"\", \"shipper_state_province\":\"\", \"shipper_postal\":\"\", \"shipper_phone\":\"\", \"return_billing_account_number\":\"\", \"return_billing_company_name\":\"\", \"return_billing_code\":\"\", \"delivery_service_code\":\"2\", \"outbound_billing_account_number\":\"270451608\", \"job_ship_company\":\"UNILEVER HPC\", \"job_ship_contact\":\"Alexander Lazar\", \"job_ship_addr1\":\"700 Sylvan\", \"job_ship_addr2\":\"\", \"job_ship_city\":\"Englewood Cliffs\", \"job_ship_state_province\":\"NJ\", \"job_ship_postal\":\"07632\", \"job_ship_phone\":\"573-395-3197\", \"job_ship_cust_email1\":\"\", \"job_ship_cust_email2\":\"\", \"ship_date\":\"\", \"parent_meter\":\"\", \"child_meter\":\"\", \"comment_box\":\"\", \"service_type\":\"\", \"weight\":\"0\", \"job_owner_comment_box\":\"\"}","weightedVote":"2.5","numVotes":"0","author":"","community":"1","dateAdded":"2014-08-12","pattern":"\"(.*?)\":\"(.*?)\"[,}]","replace":"","state":""}