{"id":"150184","urlID":"399lo","name":"x11","description":"regex or finding X11 ","content":"21.\tMozilla\/5.0 (X11; Linux x86_64; rv:28Mozilla\/5.0 (X11; Linux x86_64; rv:28.0) Gecko\/20100101 Firefox\/28.0.0) Gecko\/20100101 FirMozilla\/5.0 (X11; Linux x86_64; rv:28.0) Gecko\/20100101 Firefox\/28.0efox\/28.0 ","weightedVote":"2.5","numVotes":"0","author":"terriWillow","community":"1","dateAdded":"2014-08-07","pattern":"Mozilla\\\/5\\.0\\s\\(X11;\\sLinux\\sx86_64;\\srv:28\\.0\\)\\sGecko\\\/20100101\\sFirefox\\\/28\\.0","replace":"","state":""}